setup.py
timed_dict/timed_dict.py
timeddictionary.egg-info/PKG-INFO
timeddictionary.egg-info/SOURCES.txt
timeddictionary.egg-info/dependency_links.txt
timeddictionary.egg-info/top_level.txt