Metadata-Version: 1.1
Name: timeddictionary
Version: 0.1.1
Summary: A dictionary with key expiration and callbacks.
Home-page: https://github.com/zacernst/timed_dict
Author: Zachary Ernst
Author-email: zac.ernst@gmail.com
License: UNKNOWN
Platform: UNKNOWN
Classifier: Programming Language :: Python :: 3
Classifier: License :: OSI Approved :: MIT License
Classifier: Operating System :: OS Independent
